{
	"forge_marker": 1,
	"defaults": {
		"transform": "forge:default-block",
		"model": "cube_all"
	},
	"variants": {
		"type": {
			"copper": {
				"textures": { "all": "thermalfoundation:blocks/block_copper" }
			},
			"tin": {
				"textures": { "all": "thermalfoundation:blocks/block_tin" }
			},
			"silver": {
				"textures": { "all": "thermalfoundation:blocks/block_silver" }
			},
			"lead": {
				"textures": { "all": "thermalfoundation:blocks/block_lead" }
			},
			"nickel": {
				"textures": { "all": "thermalfoundation:blocks/block_nickel" }
			},
			"platinum": {
				"textures": { "all": "thermalfoundation:blocks/block_platinum" }
			},
			"mithril": {
				"textures": { "all": "thermalfoundation:blocks/block_mithril" }
			},
			"electrum": {
				"textures": { "all": "thermalfoundation:blocks/block_electrum" }
			},
			"invar": {
				"textures": { "all": "thermalfoundation:blocks/block_invar" }
			},
			"bronze": {
				"textures": { "all": "thermalfoundation:blocks/block_bronze" }
			},
			"signalum": {
				"textures": { "all": "thermalfoundation:blocks/block_signalum" }
			},
			"lumium": {
				"textures": { "all": "thermalfoundation:blocks/block_lumium" }
			},
			"enderium": {
				"textures": { "all": "thermalfoundation:blocks/block_enderium" }
			}
		}
	}
}